ts_soup/__init__.py
ts_soup/app.py
ts_soup/common.py
ts_soup/workers/__init__.py
ts_soup/workers/sources.py
ts_soup/workers/targets.py
ts_soup-0.2.5.dist-info/METADATA
ts_soup-0.2.5.dist-info/WHEEL
ts_soup-0.2.5.dist-info/top_level.txt
ts_soup-0.2.5.dist-info/RECORD
