Metadata-Version: 2.1
Name: ts-soup
Version: 0.2.5
Summary: date series data synchronization
Author: feihan ye
Author-email: 445280206@qq.com
Classifier: Programming Language :: Python :: 3
Classifier: License :: OSI Approved :: MIT License
Classifier: Operating System :: OS Independent
